CHANGELOG.rst
MANIFEST.in
README.rst
setup.py
src/ua2/__init__.py
src/ua2.redis.egg-info/PKG-INFO
src/ua2.redis.egg-info/SOURCES.txt
src/ua2.redis.egg-info/dependency_links.txt
src/ua2.redis.egg-info/eager_resources.txt
src/ua2.redis.egg-info/namespace_packages.txt
src/ua2.redis.egg-info/not-zip-safe
src/ua2.redis.egg-info/requires.txt
src/ua2.redis.egg-info/top_level.txt
src/ua2/redis/__init__.py
src/ua2/redis/connection.py
src/ua2/redis/pool.py