Metadata-Version: 1.0
Name: ua2.redis
Version: 0.0.2
Summary: Django wrapper for redis pool manager
Home-page: https://bitbucket.org/ua2crm/ua2.redis
Author: Vic Bukhantsov
Author-email: vic@ua2crm.com
License: BSD License
Platform: UNKNOWN
